{"series":[{"name":"AnyHashableWithAClass i2a","voluntary_cs":0,"max_rss":11517952,"data":[297724,302342],"involuntary_cs":934,"num_iters":2},{"name":"AnyHashableWithAClass i1a","voluntary_cs":0,"max_rss":11501568,"data":[295832,362886,356666,306017],"involuntary_cs":1165,"num_iters":1},{"name":"AnyHashableWithAClass i2b","voluntary_cs":0,"max_rss":11522048,"data":[314023,320257],"involuntary_cs":1290,"num_iters":2},{"name":"AnyHashableWithAClass i1b","voluntary_cs":0,"max_rss":11534336,"data":[288907,320576,942054,986654],"involuntary_cs":790,"num_iters":1},{"name":"AnyHashableWithAClass i2c","voluntary_cs":0,"max_rss":11517952,"data":[859187,465089],"involuntary_cs":1614,"num_iters":2},{"name":"AnyHashableWithAClass i1c","voluntary_cs":0,"max_rss":11534336,"data":[572066,527864,347550,295572],"involuntary_cs":1229,"num_iters":1},{"name":"AnyHashableWithAClass i2d","voluntary_cs":0,"max_rss":11546624,"data":[294541,291020],"involuntary_cs":882,"num_iters":2},{"name":"AnyHashableWithAClass i1d","voluntary_cs":0,"max_rss":11526144,"data":[285114,293088,284900,293646],"involuntary_cs":556,"num_iters":1}],"type":"num_iters","name":"AnyHashableWithAClass"}