{"series":[{"voluntary_cs":0,"data":[51028,51705,50480,50654],"name":"CharIteration_korean_unicodeScalars_Backwards i4b","involuntary_cs":750,"num_iters":4},{"voluntary_cs":0,"data":[61303,53361,48529,47884],"name":"CharIteration_korean_unicodeScalars_Backwards i4c","involuntary_cs":976,"num_iters":4},{"voluntary_cs":0,"data":[48300,50098,55943,48563],"name":"CharIteration_korean_unicodeScalars_Backwards i4a","involuntary_cs":374,"num_iters":4},{"voluntary_cs":0,"data":[50487,48026,48125,52646,51600,47941,47917,48425],"name":"CharIteration_korean_unicodeScalars_Backwards i2b","involuntary_cs":305,"num_iters":2},{"voluntary_cs":0,"data":[50458,48055,47853,48073,48359,47633,48382,48005],"name":"CharIteration_korean_unicodeScalars_Backwards i2c","involuntary_cs":315,"num_iters":2},{"voluntary_cs":0,"data":[50681,66968,48674,47809,48344,47824,48658,48490],"name":"CharIteration_korean_unicodeScalars_Backwards i2a","involuntary_cs":708,"num_iters":2},{"voluntary_cs":0,"data":[51495,53800,57958,57928,56166,54390,57406,54926],"name":"CharIteration_korean_unicodeScalars_Backwards i2d","involuntary_cs":951,"num_iters":2},{"voluntary_cs":0,"data":[49955,48044,57644,54526],"name":"CharIteration_korean_unicodeScalars_Backwards i4d","involuntary_cs":542,"num_iters":4},{"voluntary_cs":0,"data":[66730,146277,116496,63393,68052,55754,48445,49726,59353,49523,61453,50008,47547,49422,49446,48122],"name":"CharIteration_korean_unicodeScalars_Backwards i1d","involuntary_cs":679,"num_iters":1},{"voluntary_cs":0,"data":[50843,51667,47930,47982,48130,47781,48618,50753,69262,56427,52704,57566,50438,47775,47817,48151],"name":"CharIteration_korean_unicodeScalars_Backwards i1c","involuntary_cs":544,"num_iters":1},{"voluntary_cs":0,"data":[50579,52114,48257,47799,49367,48474,52089,49125,51289,50326,51479,47521,50785,48222,48402,48382],"name":"CharIteration_korean_unicodeScalars_Backwards i1b","involuntary_cs":566,"num_iters":1},{"voluntary_cs":0,"data":[49229,51561,47511,48327,48662,47863,47588,52593,48149,48112,47261,48462,48225,47950,47668,48212],"name":"CharIteration_korean_unicodeScalars_Backwards i1a","involuntary_cs":272,"num_iters":1}],"type":"num_iters","name":"CharIteration_korean_unicodeScalars_Backwards"}