{"series":[{"voluntary_cs":0,"data":[330,330,331,331,331,330,330,331,331,331,330,332,331,330,331,330,331,331,330,331],"name":"DropWhileAnySeqCntRangeLazy d","involuntary_cs":1854,"num_iters":2064},{"voluntary_cs":0,"data":[335,335,335,336,335,335,335,335,335,335,335,335,335,335,335,335,335,335,335,335],"name":"DropWhileAnySeqCntRangeLazy b","involuntary_cs":2015,"num_iters":2082},{"voluntary_cs":0,"data":[331,332,332,331,331,331,332,331,332,332,331,332,331,332,331,331,331,332,332,331],"name":"DropWhileAnySeqCntRangeLazy c","involuntary_cs":1865,"num_iters":2081},{"voluntary_cs":0,"data":[328,330,328,328,328,328,328,328,328,328,328,328,328,328,328,328,328,328,328,328],"name":"DropWhileAnySeqCntRangeLazy a","involuntary_cs":1893,"num_iters":2080}],"type":"num_iters","name":"DropWhileAnySeqCntRangeLazy"}