{"series":[{"name":"ExistentialTestTwoMethodCalls_IntValueBuffer2 i2a","voluntary_cs":1,"max_rss":11505664,"data":[69918,78697,77097,77238,77082,77246,76291,71920],"involuntary_cs":1193,"num_iters":2},{"name":"ExistentialTestTwoMethodCalls_IntValueBuffer2 i2b","voluntary_cs":0,"max_rss":11501568,"data":[71777,79805,77736,76871,75884,71609,72087,73351],"involuntary_cs":995,"num_iters":2},{"name":"ExistentialTestTwoMethodCalls_IntValueBuffer2 i2c","voluntary_cs":0,"max_rss":11505664,"data":[74476,76580,69934,70946,70251,72614,74744,74135],"involuntary_cs":841,"num_iters":2},{"name":"ExistentialTestTwoMethodCalls_IntValueBuffer2 i2d","voluntary_cs":0,"max_rss":11505664,"data":[70115,84495,78120,79183,89322,82604,74071,70467],"involuntary_cs":1098,"num_iters":2},{"name":"ExistentialTestTwoMethodCalls_IntValueBuffer2 i2e","voluntary_cs":0,"max_rss":11493376,"data":[70572,69973,72157,78505,77527,73837,70105,73674],"involuntary_cs":868,"num_iters":2},{"name":"ExistentialTestTwoMethodCalls_IntValueBuffer2 i1a","voluntary_cs":0,"max_rss":11485184,"data":[69958,70097,69894,70410,69895,71726,78034,83107,74122,77854,79064,73516,84199,74655,75286,70787],"involuntary_cs":964,"num_iters":1},{"name":"ExistentialTestTwoMethodCalls_IntValueBuffer2 i1b","voluntary_cs":0,"max_rss":11493376,"data":[79190,131554,148323,155157,108132,137901,135500,191830,123824,169066,103294,172414,141380,132070,119540,95278],"involuntary_cs":1367,"num_iters":1},{"name":"ExistentialTestTwoMethodCalls_IntValueBuffer2 i1c","voluntary_cs":0,"max_rss":11517952,"data":[69621,70394,69677,70747,69772,70145,79460,78729,75531,77692,78905,75967,75721,71927,75021,70032],"involuntary_cs":948,"num_iters":1},{"name":"ExistentialTestTwoMethodCalls_IntValueBuffer2 i1d","voluntary_cs":0,"max_rss":11493376,"data":[70156,69908,69892,70868,69864,70484,74772,76855,83278,76064,78323,73202,80136,75317,76489,72824],"involuntary_cs":792,"num_iters":1},{"name":"ExistentialTestTwoMethodCalls_IntValueBuffer2 i1e","voluntary_cs":0,"max_rss":11489280,"data":[72148,76582,73543,75938,76291,77033,77969,80776,77791,74633,76786,78199,73696,77102,71091,75097],"involuntary_cs":1201,"num_iters":1}],"type":"num_iters","name":"ExistentialTestTwoMethodCalls_IntValueBuffer2"}