{"series":[{"name":"ExistentialTestArrayMutating_ClassValueBuffer3 i4a","voluntary_cs":0,"max_rss":4657152,"data":[76328,76516,76809,76319],"involuntary_cs":111,"num_iters":4},{"name":"ExistentialTestArrayMutating_ClassValueBuffer3 i2a","voluntary_cs":0,"max_rss":4681728,"data":[76562,76997,76784,79083,76858,76260,78922,78936],"involuntary_cs":113,"num_iters":2},{"name":"ExistentialTestArrayMutating_ClassValueBuffer3 i1a","voluntary_cs":0,"max_rss":4673536,"data":[78822,78687,78741,78764,78671,78748,78983,78908,78649,77784,78883,78730,78830,78224,78712,78799],"involuntary_cs":111,"num_iters":1},{"name":"ExistentialTestArrayMutating_ClassValueBuffer3 i4b","voluntary_cs":0,"max_rss":4673536,"data":[78283,78630,78644,78655],"involuntary_cs":114,"num_iters":4},{"name":"ExistentialTestArrayMutating_ClassValueBuffer3 i2b","voluntary_cs":0,"max_rss":4681728,"data":[79254,79548,78623,78752,78981,78947,78934,79030],"involuntary_cs":127,"num_iters":2},{"name":"ExistentialTestArrayMutating_ClassValueBuffer3 i1b","voluntary_cs":0,"max_rss":4673536,"data":[79036,78730,78738,78687,78691,78700,78875,79139,78788,78410,78812,78941,78893,78927,78715,78837],"involuntary_cs":127,"num_iters":1},{"name":"ExistentialTestArrayMutating_ClassValueBuffer3 i4c","voluntary_cs":0,"max_rss":4673536,"data":[80026,80674,80508,80162],"involuntary_cs":122,"num_iters":4},{"name":"ExistentialTestArrayMutating_ClassValueBuffer3 i2c","voluntary_cs":2,"max_rss":4681728,"data":[79095,78557,78972,79480,78533,79480,78643,79463],"involuntary_cs":111,"num_iters":2},{"name":"ExistentialTestArrayMutating_ClassValueBuffer3 i1c","voluntary_cs":0,"max_rss":4665344,"data":[76737,76200,76360,79603,76679,77549,79363,78975,78928,79327,77005,79180,79140,76840,79433,78949],"involuntary_cs":114,"num_iters":1},{"name":"ExistentialTestArrayMutating_ClassValueBuffer3 i4d","voluntary_cs":0,"max_rss":4673536,"data":[78527,78557,78710,78638],"involuntary_cs":119,"num_iters":4},{"name":"ExistentialTestArrayMutating_ClassValueBuffer3 i2d","voluntary_cs":0,"max_rss":4681728,"data":[78853,78438,78733,78434,78395,78625,78682,78604],"involuntary_cs":121,"num_iters":2},{"name":"ExistentialTestArrayMutating_ClassValueBuffer3 i1d","voluntary_cs":0,"max_rss":4673536,"data":[78062,78537,78090,78899,78967,79276,78840,78278,78533,78673,78760,78805,78455,78651,78765,78607],"involuntary_cs":106,"num_iters":1}],"type":"num_iters","name":"ExistentialTestArrayMutating_ClassValueBuffer3"}