{"series":[{"name":"ExistentialTestMutating_ClassValueBuffer4 i1a","voluntary_cs":0,"max_rss":11485184,"data":[263416,362654,362240,409459],"involuntary_cs":641,"num_iters":1},{"name":"ExistentialTestMutating_ClassValueBuffer4 i1b","voluntary_cs":0,"max_rss":11493376,"data":[315137,262360,245458,247468],"involuntary_cs":611,"num_iters":1},{"name":"ExistentialTestMutating_ClassValueBuffer4 i1c","voluntary_cs":0,"max_rss":11513856,"data":[164198,225372,251662,239126],"involuntary_cs":427,"num_iters":1},{"name":"ExistentialTestMutating_ClassValueBuffer4 i1d","voluntary_cs":0,"max_rss":11509760,"data":[246064,247142,229709,276898],"involuntary_cs":343,"num_iters":1},{"name":"ExistentialTestMutating_ClassValueBuffer4 i1e","voluntary_cs":0,"max_rss":11509760,"data":[164053,226398,288710,271346],"involuntary_cs":362,"num_iters":1},{"name":"ExistentialTestMutating_ClassValueBuffer4 i1f","voluntary_cs":0,"max_rss":11485184,"data":[176511,241916,244611,251868],"involuntary_cs":435,"num_iters":1},{"name":"ExistentialTestMutating_ClassValueBuffer4 i2a","voluntary_cs":0,"max_rss":11497472,"data":[228671,266138],"involuntary_cs":645,"num_iters":2},{"name":"ExistentialTestMutating_ClassValueBuffer4 i2b","voluntary_cs":0,"max_rss":11505664,"data":[203107,277890],"involuntary_cs":437,"num_iters":2},{"name":"ExistentialTestMutating_ClassValueBuffer4 i2c","voluntary_cs":0,"max_rss":11505664,"data":[191780,272723],"involuntary_cs":376,"num_iters":2},{"name":"ExistentialTestMutating_ClassValueBuffer4 i2d","voluntary_cs":0,"max_rss":11513856,"data":[243288,239134],"involuntary_cs":657,"num_iters":2}],"type":"num_iters","name":"ExistentialTestMutating_ClassValueBuffer4"}