{"series":[{"name":"ExistentialTestArrayTwoMethodCalls_IntValueBuffer4 i4a","voluntary_cs":0,"max_rss":11530240,"data":[74809,75344,72458,72474],"involuntary_cs":430,"num_iters":4},{"name":"ExistentialTestArrayTwoMethodCalls_IntValueBuffer4 i2a","voluntary_cs":0,"max_rss":11542528,"data":[72696,72827,73324,71759,72285,71882,72004,72499],"involuntary_cs":317,"num_iters":2},{"name":"ExistentialTestArrayTwoMethodCalls_IntValueBuffer4 i1a","voluntary_cs":0,"max_rss":11526144,"data":[73263,72234,72693,72654,72207,72982,72183,72189,72340,71963,73311,73101,72022,72166,72545,71877],"involuntary_cs":437,"num_iters":1},{"name":"ExistentialTestArrayTwoMethodCalls_IntValueBuffer4 i4b","voluntary_cs":0,"max_rss":11526144,"data":[72557,72163,72309,73333],"involuntary_cs":367,"num_iters":4},{"name":"ExistentialTestArrayTwoMethodCalls_IntValueBuffer4 i2b","voluntary_cs":0,"max_rss":11546624,"data":[73218,73781,73504,73568,73546,73312,73340,73257],"involuntary_cs":465,"num_iters":2},{"name":"ExistentialTestArrayTwoMethodCalls_IntValueBuffer4 i1b","voluntary_cs":0,"max_rss":11534336,"data":[72426,72880,72925,75077,73357,73891,73115,73164,72501,73107,72747,73173,72701,72562,72882,72080],"involuntary_cs":504,"num_iters":1},{"name":"ExistentialTestArrayTwoMethodCalls_IntValueBuffer4 i4c","voluntary_cs":0,"max_rss":11530240,"data":[73131,73589,73459,72927],"involuntary_cs":381,"num_iters":4},{"name":"ExistentialTestArrayTwoMethodCalls_IntValueBuffer4 i2c","voluntary_cs":0,"max_rss":11542528,"data":[72214,72781,72775,71878,73551,73438,72657,72474],"involuntary_cs":477,"num_iters":2},{"name":"ExistentialTestArrayTwoMethodCalls_IntValueBuffer4 i1c","voluntary_cs":0,"max_rss":11534336,"data":[76073,72658,73152,73224,72739,72738,71792,72257,72898,71479,71781,71794,71943,71926,71484,71530],"involuntary_cs":268,"num_iters":1},{"name":"ExistentialTestArrayTwoMethodCalls_IntValueBuffer4 i4d","voluntary_cs":0,"max_rss":11526144,"data":[72298,71751,71289,71477],"involuntary_cs":169,"num_iters":4},{"name":"ExistentialTestArrayTwoMethodCalls_IntValueBuffer4 i2d","voluntary_cs":0,"max_rss":11554816,"data":[71531,72021,71552,87646,75854,86537,84502,71525],"involuntary_cs":141,"num_iters":2},{"name":"ExistentialTestArrayTwoMethodCalls_IntValueBuffer4 i1d","voluntary_cs":0,"max_rss":11542528,"data":[72236,71746,72060,72410,72532,71752,71814,71761,71846,71835,71806,72058,71842,71800,71822,71860],"involuntary_cs":143,"num_iters":1}],"type":"num_iters","name":"ExistentialTestArrayTwoMethodCalls_IntValueBuffer4"}