{"series":[{"name":"ExistentialTestArrayOneMethodCall_ClassValueBuffer1 i4a","voluntary_cs":0,"max_rss":11513856,"data":[135804,156885,152228,141102],"involuntary_cs":1108,"num_iters":4},{"name":"ExistentialTestArrayOneMethodCall_ClassValueBuffer1 i2a","voluntary_cs":0,"max_rss":11526144,"data":[103953,155505,156707,141151,135228,153725,153914,173661],"involuntary_cs":975,"num_iters":2},{"name":"ExistentialTestArrayOneMethodCall_ClassValueBuffer1 i1a","voluntary_cs":0,"max_rss":11530240,"data":[69446,132463,139351,183413,139189,168392,192181,180339,132488,144871,133164,143483,131043,147918,131518,130868],"involuntary_cs":1045,"num_iters":1},{"name":"ExistentialTestArrayOneMethodCall_ClassValueBuffer1 i4b","voluntary_cs":0,"max_rss":11513856,"data":[132960,145260,159992,158756],"involuntary_cs":1771,"num_iters":4},{"name":"ExistentialTestArrayOneMethodCall_ClassValueBuffer1 i2b","voluntary_cs":0,"max_rss":11542528,"data":[94495,137286,142025,130689,164266,149098,170445,149640],"involuntary_cs":771,"num_iters":2},{"name":"ExistentialTestArrayOneMethodCall_ClassValueBuffer1 i1b","voluntary_cs":0,"max_rss":11517952,"data":[65038,106763,119775,154893,129362,205108,123630,131692,159299,168959,148001,127987,182622,153118,133570,148881],"involuntary_cs":1332,"num_iters":1},{"name":"ExistentialTestArrayOneMethodCall_ClassValueBuffer1 i4c","voluntary_cs":0,"max_rss":11513856,"data":[133689,130795,160759,139105],"involuntary_cs":776,"num_iters":4},{"name":"ExistentialTestArrayOneMethodCall_ClassValueBuffer1 i2c","voluntary_cs":0,"max_rss":11526144,"data":[75249,124837,160164,142523,167046,136998,148662,156337],"involuntary_cs":896,"num_iters":2},{"name":"ExistentialTestArrayOneMethodCall_ClassValueBuffer1 i1c","voluntary_cs":0,"max_rss":11517952,"data":[66585,92187,117588,180104,154496,134877,177436,169736,186331,160701,133573,142130,138578,134549,128486,143484],"involuntary_cs":848,"num_iters":1},{"name":"ExistentialTestArrayOneMethodCall_ClassValueBuffer1 i4d","voluntary_cs":0,"max_rss":11530240,"data":[109633,165105,150351,161205],"involuntary_cs":678,"num_iters":4},{"name":"ExistentialTestArrayOneMethodCall_ClassValueBuffer1 i2d","voluntary_cs":0,"max_rss":11530240,"data":[85141,137500,171622,157205,164816,151609,137220,134724],"involuntary_cs":776,"num_iters":2},{"name":"ExistentialTestArrayOneMethodCall_ClassValueBuffer1 i1d","voluntary_cs":0,"max_rss":11522048,"data":[65311,88402,221799,176118,131317,140030,133072,145904,130860,143788,121674,214214,227793,142304,146838,163405],"involuntary_cs":1063,"num_iters":1}],"type":"num_iters","name":"ExistentialTestArrayOneMethodCall_ClassValueBuffer1"}