{"series":[{"name":"LazilyFilteredArrays i1a","voluntary_cs":0,"max_rss":64061440,"data":[835580,832594],"involuntary_cs":154,"num_iters":1},{"name":"LazilyFilteredArrays i1b","voluntary_cs":0,"max_rss":64098304,"data":[840626,832002],"involuntary_cs":147,"num_iters":1},{"name":"LazilyFilteredArrays i1c","voluntary_cs":0,"max_rss":64274432,"data":[846258,835750],"involuntary_cs":142,"num_iters":1},{"name":"LazilyFilteredArrays i1d","voluntary_cs":0,"max_rss":64278528,"data":[836366,835111],"involuntary_cs":146,"num_iters":1},{"name":"LazilyFilteredArrays i1e","voluntary_cs":0,"max_rss":64270336,"data":[840983,833355],"involuntary_cs":151,"num_iters":1},{"name":"LazilyFilteredArrays i1f","voluntary_cs":0,"max_rss":64266240,"data":[894860,886763],"involuntary_cs":170,"num_iters":1},{"name":"LazilyFilteredArrays i1g","voluntary_cs":0,"max_rss":64274432,"data":[841891,846215],"involuntary_cs":168,"num_iters":1},{"name":"LazilyFilteredArrays i1h","voluntary_cs":0,"max_rss":64282624,"data":[894127,893385],"involuntary_cs":154,"num_iters":1},{"name":"LazilyFilteredArrays i1i","voluntary_cs":0,"max_rss":64065536,"data":[845557,831580],"involuntary_cs":149,"num_iters":1},{"name":"LazilyFilteredArrays i1j","voluntary_cs":0,"max_rss":64532480,"data":[845760,831868],"involuntary_cs":193,"num_iters":1}],"type":"num_iters","name":"LazilyFilteredArrays"}