{"series":[{"voluntary_cs":0,"data":[129302,127420,128533,129057,126536,124974,125621,125023],"name":"ReversedBidirectional i1a","involuntary_cs":365,"num_iters":1},{"voluntary_cs":0,"data":[128042,128174,127399,126972],"name":"ReversedBidirectional i2a","involuntary_cs":296,"num_iters":2},{"voluntary_cs":0,"data":[125056,130300,132145,129196],"name":"ReversedBidirectional i2c","involuntary_cs":424,"num_iters":2},{"voluntary_cs":0,"data":[125656,124052,124548,124252],"name":"ReversedBidirectional i2b","involuntary_cs":135,"num_iters":2},{"voluntary_cs":0,"data":[127436,123629,122929,122915],"name":"ReversedBidirectional i2d","involuntary_cs":220,"num_iters":2},{"voluntary_cs":0,"data":[123756,123688,129296,134979,129773,124712,123330,126185],"name":"ReversedBidirectional i1b","involuntary_cs":377,"num_iters":1},{"voluntary_cs":0,"data":[123247,126785,130173,127987,123016,124048,123265,122943],"name":"ReversedBidirectional i1d","involuntary_cs":314,"num_iters":1},{"voluntary_cs":0,"data":[130351,123877],"name":"ReversedBidirectional i4b","involuntary_cs":434,"num_iters":4},{"voluntary_cs":0,"data":[124128,122881],"name":"ReversedBidirectional i4c","involuntary_cs":195,"num_iters":4},{"voluntary_cs":0,"data":[124459,125884],"name":"ReversedBidirectional i4d","involuntary_cs":278,"num_iters":4},{"voluntary_cs":0,"data":[127437,125676,125155,125140,125042,122796,125052,124818],"name":"ReversedBidirectional i1c","involuntary_cs":156,"num_iters":1},{"voluntary_cs":0,"data":[128229,130547],"name":"ReversedBidirectional i4a","involuntary_cs":241,"num_iters":4}],"type":"num_iters","name":"ReversedBidirectional"}