{"series":[{"voluntary_cs":null,"data":[783,801,802,799,784,783,784,784,785,783,784,783,785,783,784,783,784,784,783,784],"name":"StringFromLongWholeSubstring i0a","involuntary_cs":null,"num_iters":1150},{"voluntary_cs":null,"data":[811,825,828,825,809,808,785,787,790,789,808,788,809,809,788,790,809,787,809,809],"name":"StringFromLongWholeSubstring i0b","involuntary_cs":null,"num_iters":1275},{"voluntary_cs":null,"data":[807,829,810,807,794,787,808,807,786,791,808,787,807,806,788,808,807,787,807,787],"name":"StringFromLongWholeSubstring i0c","involuntary_cs":null,"num_iters":1274},{"voluntary_cs":null,"data":[807,808,804,787,788,789,791,788,790,791,788,789,788,789,793,789,790,788,787,787],"name":"StringFromLongWholeSubstring i0d","involuntary_cs":null,"num_iters":1272}],"type":"num_iters","name":"StringFromLongWholeSubstring"}