{"series":[{"name":"PrefixAnyCollectionLazy i1a","voluntary_cs":0,"max_rss":11653120,"data":[566880,885950],"involuntary_cs":572,"num_iters":1},{"name":"PrefixAnyCollectionLazy i1b","voluntary_cs":0,"max_rss":11644928,"data":[595661,782922],"involuntary_cs":614,"num_iters":1},{"name":"PrefixAnyCollectionLazy i1c","voluntary_cs":0,"max_rss":11640832,"data":[757190,702835],"involuntary_cs":575,"num_iters":1},{"name":"PrefixAnyCollectionLazy i1d","voluntary_cs":0,"max_rss":11649024,"data":[678542,693664],"involuntary_cs":499,"num_iters":1}],"type":"num_iters","name":"PrefixAnyCollectionLazy"}