{"series":[{"name":"ExistentialTestArrayTwoMethodCalls_IntValueBuffer4 i2a","voluntary_cs":0,"max_rss":11542528,"data":[71664,82467,74439,79462,73887,76898,76346,73061],"involuntary_cs":656,"num_iters":2},{"name":"ExistentialTestArrayTwoMethodCalls_IntValueBuffer4 i2b","voluntary_cs":0,"max_rss":11542528,"data":[73798,73981,88135,79175,75983,78519,191829,140649],"involuntary_cs":991,"num_iters":2},{"name":"ExistentialTestArrayTwoMethodCalls_IntValueBuffer4 i2c","voluntary_cs":0,"max_rss":11542528,"data":[101739,154115,149803,155844,113029,78955,83259,80304],"involuntary_cs":889,"num_iters":2},{"name":"ExistentialTestArrayTwoMethodCalls_IntValueBuffer4 i2d","voluntary_cs":0,"max_rss":11542528,"data":[81212,75003,75347,75540,79473,81407,81123,79072],"involuntary_cs":1163,"num_iters":2},{"name":"ExistentialTestArrayTwoMethodCalls_IntValueBuffer4 i2e","voluntary_cs":0,"max_rss":11542528,"data":[72890,73738,80770,82886,82224,79511,80370,80480],"involuntary_cs":944,"num_iters":2},{"name":"ExistentialTestArrayTwoMethodCalls_IntValueBuffer4 i1a","voluntary_cs":0,"max_rss":11534336,"data":[74057,71984,73004,74134,77779,76471,160614,82175,86194,73378,72386,77544,77270,75777,73054,72522],"involuntary_cs":847,"num_iters":1},{"name":"ExistentialTestArrayTwoMethodCalls_IntValueBuffer4 i1b","voluntary_cs":0,"max_rss":11534336,"data":[72432,73536,72431,73890,76774,90896,93649,87961,88434,84878,74529,75575,73903,72880,80109,74436],"involuntary_cs":737,"num_iters":1},{"name":"ExistentialTestArrayTwoMethodCalls_IntValueBuffer4 i1c","voluntary_cs":0,"max_rss":11550720,"data":[78134,72531,72786,72534,79661,84031,77773,82013,81516,78193,85493,72581,71660,73527,73606,72160],"involuntary_cs":813,"num_iters":1},{"name":"ExistentialTestArrayTwoMethodCalls_IntValueBuffer4 i1d","voluntary_cs":0,"max_rss":11534336,"data":[72009,71433,74566,75217,72235,74367,73735,73713,72481,73696,73129,71429,71856,73602,71647,71891],"involuntary_cs":729,"num_iters":1},{"name":"ExistentialTestArrayTwoMethodCalls_IntValueBuffer4 i1e","voluntary_cs":0,"max_rss":11534336,"data":[71627,73392,75269,72133,71461,72721,73082,71739,71555,71956,71496,71624,71566,71766,71787,71272],"involuntary_cs":319,"num_iters":1}],"type":"num_iters","name":"ExistentialTestArrayTwoMethodCalls_IntValueBuffer4"}