{"series":[{"name":"SuffixAnySequenceLazy i4a","voluntary_cs":0,"max_rss":11649024,"data":[44032,72639,56721,54207],"involuntary_cs":551,"num_iters":4},{"name":"SuffixAnySequenceLazy i2a","voluntary_cs":0,"max_rss":11649024,"data":[44314,55573,61100,87719,57709,57666,85520,60700],"involuntary_cs":378,"num_iters":2},{"name":"SuffixAnySequenceLazy i1a","voluntary_cs":0,"max_rss":11649024,"data":[55192,62330,59210,59440,59312,53721,63223,52730,58449,57114,53241,59251,59501,60485,56092,60290],"involuntary_cs":528,"num_iters":1},{"name":"SuffixAnySequenceLazy i4b","voluntary_cs":0,"max_rss":11636736,"data":[36120,53933,61702,74029],"involuntary_cs":544,"num_iters":4},{"name":"SuffixAnySequenceLazy i2b","voluntary_cs":0,"max_rss":11653120,"data":[48121,65186,70425,55161,57540,74038,60098,92283],"involuntary_cs":433,"num_iters":2},{"name":"SuffixAnySequenceLazy i1b","voluntary_cs":0,"max_rss":11644928,"data":[36621,37597,36277,41803,81381,102342,53208,58313,61724,70988,110014,49812,62211,63863,74502,107858],"involuntary_cs":670,"num_iters":1},{"name":"SuffixAnySequenceLazy i4c","voluntary_cs":0,"max_rss":11636736,"data":[38632,70564,56992,59050],"involuntary_cs":530,"num_iters":4},{"name":"SuffixAnySequenceLazy i2c","voluntary_cs":0,"max_rss":11653120,"data":[37485,40709,49963,54033,88308,65434,67307,89224],"involuntary_cs":393,"num_iters":2},{"name":"SuffixAnySequenceLazy i1c","voluntary_cs":1,"max_rss":11644928,"data":[36945,35969,36096,42641,48547,58017,56668,86616,71956,72297,57452,84991,91062,59764,70727,49201],"involuntary_cs":583,"num_iters":1},{"name":"SuffixAnySequenceLazy i4d","voluntary_cs":0,"max_rss":11649024,"data":[51248,70605,66812,56961],"involuntary_cs":689,"num_iters":4},{"name":"SuffixAnySequenceLazy i2d","voluntary_cs":0,"max_rss":11649024,"data":[36664,47898,86462,58820,77600,70381,56043,57458],"involuntary_cs":391,"num_iters":2},{"name":"SuffixAnySequenceLazy i1d","voluntary_cs":0,"max_rss":11649024,"data":[37065,36682,35465,36398,53794,50309,59733,66545,45058,60166,54616,58969,60599,59789,51467,61292],"involuntary_cs":393,"num_iters":1}],"type":"num_iters","name":"SuffixAnySequenceLazy"}