{"series":[{"name":"ExistentialTestArrayShift_ClassValueBuffer3 i1a","voluntary_cs":0,"max_rss":11522048,"data":[881143,1191700],"involuntary_cs":693,"num_iters":1},{"name":"ExistentialTestArrayShift_ClassValueBuffer3 i1b","voluntary_cs":0,"max_rss":11542528,"data":[988289,1056400],"involuntary_cs":831,"num_iters":1},{"name":"ExistentialTestArrayShift_ClassValueBuffer3 i1c","voluntary_cs":0,"max_rss":11517952,"data":[1015620,1206066],"involuntary_cs":958,"num_iters":1},{"name":"ExistentialTestArrayShift_ClassValueBuffer3 i1d","voluntary_cs":0,"max_rss":11522048,"data":[1444232,1517787],"involuntary_cs":1194,"num_iters":1},{"name":"ExistentialTestArrayShift_ClassValueBuffer3 i1e","voluntary_cs":0,"max_rss":11493376,"data":[1186246,1258977],"involuntary_cs":1070,"num_iters":1},{"name":"ExistentialTestArrayShift_ClassValueBuffer3 i1f","voluntary_cs":0,"max_rss":11530240,"data":[1243356,1095045],"involuntary_cs":1044,"num_iters":1},{"name":"ExistentialTestArrayShift_ClassValueBuffer3 i1g","voluntary_cs":0,"max_rss":11493376,"data":[1096155,1199970],"involuntary_cs":1008,"num_iters":1},{"name":"ExistentialTestArrayShift_ClassValueBuffer3 i1h","voluntary_cs":0,"max_rss":11530240,"data":[1003985,1194717],"involuntary_cs":884,"num_iters":1},{"name":"ExistentialTestArrayShift_ClassValueBuffer3 i1i","voluntary_cs":0,"max_rss":11522048,"data":[1023312,1024945],"involuntary_cs":756,"num_iters":1},{"name":"ExistentialTestArrayShift_ClassValueBuffer3 i1j","voluntary_cs":0,"max_rss":11505664,"data":[967754,1107132],"involuntary_cs":629,"num_iters":1}],"type":"num_iters","name":"ExistentialTestArrayShift_ClassValueBuffer3"}