{"series":[{"name":"ExistentialTestOneMethodCall_ClassValueBuffer4 i4a","voluntary_cs":0,"max_rss":11485184,"data":[49415,49262,53561,48114],"involuntary_cs":898,"num_iters":4},{"name":"ExistentialTestOneMethodCall_ClassValueBuffer4 i2a","voluntary_cs":0,"max_rss":11493376,"data":[48916,50297,48900,48777,49492,48896,48307,48418],"involuntary_cs":433,"num_iters":2},{"name":"ExistentialTestOneMethodCall_ClassValueBuffer4 i1a","voluntary_cs":0,"max_rss":11485184,"data":[48461,48084,48447,48218,48383,48651,48886,48531,48153,50825,48382,48869,48119,48519,48104,47972],"involuntary_cs":247,"num_iters":1},{"name":"ExistentialTestOneMethodCall_ClassValueBuffer4 i4b","voluntary_cs":0,"max_rss":11481088,"data":[48181,48508,48374,48080],"involuntary_cs":260,"num_iters":4},{"name":"ExistentialTestOneMethodCall_ClassValueBuffer4 i2b","voluntary_cs":0,"max_rss":11489280,"data":[48294,48186,49348,48474,48513,48296,48443,48075],"involuntary_cs":292,"num_iters":2},{"name":"ExistentialTestOneMethodCall_ClassValueBuffer4 i1b","voluntary_cs":0,"max_rss":11497472,"data":[48214,48706,48452,48113,49822,48543,48061,48627,48198,47925,48254,48098,48616,48513,48313,48406],"involuntary_cs":331,"num_iters":1},{"name":"ExistentialTestOneMethodCall_ClassValueBuffer4 i4c","voluntary_cs":0,"max_rss":11481088,"data":[48714,48280,48362,48702],"involuntary_cs":317,"num_iters":4},{"name":"ExistentialTestOneMethodCall_ClassValueBuffer4 i2c","voluntary_cs":0,"max_rss":11493376,"data":[48456,48347,48275,48219,48530,48283,48339,48472],"involuntary_cs":269,"num_iters":2},{"name":"ExistentialTestOneMethodCall_ClassValueBuffer4 i1c","voluntary_cs":0,"max_rss":11489280,"data":[48114,50448,48363,48832,48150,48549,48502,48064,48878,50771,48673,48356,49476,47677,49456,48705],"involuntary_cs":397,"num_iters":1},{"name":"ExistentialTestOneMethodCall_ClassValueBuffer4 i4d","voluntary_cs":0,"max_rss":11485184,"data":[48440,48460,48642,48444],"involuntary_cs":345,"num_iters":4},{"name":"ExistentialTestOneMethodCall_ClassValueBuffer4 i2d","voluntary_cs":0,"max_rss":11497472,"data":[49222,48375,48714,48247,48988,49289,48163,48407],"involuntary_cs":422,"num_iters":2},{"name":"ExistentialTestOneMethodCall_ClassValueBuffer4 i1d","voluntary_cs":0,"max_rss":11493376,"data":[48425,49447,48650,48195,48297,48620,48257,48603,48571,48440,48141,48890,47916,48632,48737,48120],"involuntary_cs":234,"num_iters":1}],"type":"num_iters","name":"ExistentialTestOneMethodCall_ClassValueBuffer4"}